django_svg_templatetag-1.0.0.dist-info/DESCRIPTION.rst
django_svg_templatetag-1.0.0.dist-info/METADATA
django_svg_templatetag-1.0.0.dist-info/RECORD
django_svg_templatetag-1.0.0.dist-info/WHEEL
django_svg_templatetag-1.0.0.dist-info/metadata.json
django_svg_templatetag-1.0.0.dist-info/top_level.txt
svg_templatetag/__init__.py
svg_templatetag/templatetags/__init__.py
svg_templatetag/templatetags/svg.py
