Metadata-Version: 2.0
Name: django-svg-templatetag
Version: 1.0.0
Summary: Inject a SVG file into your Django template.
Home-page: https://github.com/Mediamoose/django-svg-templatetag
Author: Sven Groot (Mediamoose)
Author-email: sven@mediamoose.nl
License: MIT
Keywords: django-svg-templatetag
Platform: UNKNOWN
Classifier: Development Status :: 5 - Production/Stable
Classifier: Framework :: Django
Classifier: Framework :: Django :: 1.7
Classifier: Framework :: Django :: 1.8
Classifier: Framework :: Django :: 1.9
Classifier: Framework :: Django :: 1.10
Classifier: Intended Audience :: Developers
Classifier: License :: OSI Approved :: BSD License
Classifier: Natural Language :: English
Classifier: Programming Language :: Python :: 2
Classifier: Programming Language :: Python :: 2.7
Classifier: Programming Language :: Python :: 3
Classifier: Programming Language :: Python :: 3.2
Classifier: Programming Language :: Python :: 3.3
Classifier: Programming Language :: Python :: 3.4
Classifier: Programming Language :: Python :: 3.5
